GCSizeMatchedControls/GCSizeMatchedControls.py
GCSizeMatchedControls/__init__.py
GCSizeMatchedControls/__main__.py
GCSizeMatchedControls/_version.py
GCSizeMatchedControls-1.0.3.dist-info/LICENSE
GCSizeMatchedControls-1.0.3.dist-info/METADATA
GCSizeMatchedControls-1.0.3.dist-info/WHEEL
GCSizeMatchedControls-1.0.3.dist-info/entry_points.txt
GCSizeMatchedControls-1.0.3.dist-info/top_level.txt
GCSizeMatchedControls-1.0.3.dist-info/RECORD
