Metadata-Version: 2.1
Name: GCSizeMatchedControls
Version: 1.0.3
Summary: randomly select control genomic regions
Home-page: https://pypi.org/project/GCSizeMatchedControls/
Author: Benxia Hu
Author-email: hubenxia@gmail.com
Classifier: Programming Language :: Python :: 3
Classifier: License :: OSI Approved :: MIT License
Classifier: Operating System :: OS Independent
Requires-Python: >=3.12
License-File: LICENSE
Requires-Dist: numpy
Requires-Dist: pandas
Requires-Dist: argparse
Requires-Dist: pybedtools
Requires-Dist: pysam
